{
    "tracks": [
        {
            "spotifyURI": "spotify:track:1gkzmB8NwKDFgKvZDSG6qU",
            "starttime": 63400,
            "title": "En F\u00f6r Alla F\u00f6r En",
            "artist": "Tre Kronor"
        },
        {
            "spotifyURI": "spotify:track:0picsemJCUPEpjkrhg7IGl",
            "starttime": 123500,
            "title": "Mera m\u00e5l",
            "artist": "Markoolio"
        },
        {
            "spotifyURI": "spotify:track:08e3oeRV88CYNxDhwvH1lJ",
            "starttime": 60500,
            "title": "In med bollen",
            "artist": "Markoolio"
        },
        {
            "spotifyURI": "spotify:track:2McQQA5nCLVL0XvzcxWhFC",
            "starttime": 20000,
            "artist": "The Bouncing Souls",
            "title": "Ole"
        },
        {
            "spotifyURI": "spotify:track:1bCmvezFg5MRcENzCGG1Cy",
            "starttime": 87400,
            "artist": "The Fratellis",
            "title": "Chelsea Dagger"
        },
        {
            "spotifyURI": "spotify:track:2E68HPSmJxetiG8xjkNAJ3",
            "starttime": 15600,
            "artist": "Mickie Krause",
            "title": "D\u00fcp D\u00fcp - Mallorca Version"
        },
        {
            "spotifyURI": "spotify:track:1mhrSBCtNxoJKRmtb4RGDN",
            "starttime": 0,
            "artist": "Fred Coury",
            "title": "Power Ride 2010 (La Kings Goal Song)"
        }
    ]
}